{
  "explore-ittilia": "Ontdek Ittilia",
  "page-wiki": "Wiki",
  "page-map": "Kaart",
  "page-lineage": "Bloedlijn",
  "page-classes": "Rollen",
  "name": "Naam",
  "initiative": "Initiatief",
  "max-hp": "Max Levenspunten",
  "stat-hp": "Levenspunten",
  "stat-mr": "Moraal",
  "stat-pp": "Perceptie",
  "stat-ac": "Pantserrang",
  "stat-lvl": "Rang",
  "stat-spd": "Snelheid",
  "enemy": "Vijand",
  "ally": "Bondgenoot",
  "player": "Speler",
  "action-clear": "Verwijderen",
  "action-add": "Voeg Toe",
  "action-import": "Importeren",
  "action-save": "Opslaan",
  "action-back": "Terug",
  "action-show-menu": "Toon Menu",
  "action-hide-menu": "Verberg Menu",
  "groupname": "Groepsnaam",
  "filename": "Bestandsnaam",
  "description": "Beschrijving",
  "item-name": "Item Naam",
  "req-attune": "Vereist Binding",
  "round": "Ronde",
  "turn": "Beurt",
  "action-sort": "Sorteer",
  "action-reset": "Reset",
  "monster-xp": "Totale XP",
  "difficulty": "Moeilijkheid",
  "easy": "Makkelijk",
  "medium": "Gemiddeld",
  "hard": "Moeilijk",
  "deadly": "Dodelijk",
  "ability-str": "Kracht",
  "ability-dex": "Finesse",
  "ability-con": "Vitaliteit",
  "ability-int": "Intelligentie",
  "ability-wis": "Wijsheid",
  "ability-cha": "Charisma",
  "door-reinforced": "Verstevigd",
  "door-wood": "Houten Deur",
  "door-iron": "IJzeren Deur",
  "door-stone": "Stenen Deur",
  "door-portcullis": "Valhek",
  "door-locked": "Gesloten",
  "door-stuck": "Klem",
  "door-secret": "Geheim",
  "lineage-label": "Bloedlijnen",
  "lineage-urr": "Urr",
  "lineage-urr-brief": "...",
  "lineage-urr-dranan": "Urr'Dranan",
  "lineage-urr-dranan-brief": "...",
  "lineage-elves": "Elven",
  "lineage-elves-brief": "...",
  "lineage-ghimach": "Ghímach",
  "lineage-ghimach-brief": "...",
  "lineage-curse": "Beestenvloek",
  "lineage-curse-brief": "..."
}